Metadata-Version: 2.1
Name: DataStructures10
Version: 1.0.1
Summary: Data structure components module
Home-page: UNKNOWN
Author: Dereck Jos
Author-email: derijos55@gmail.com
License: MIT
Keywords: data_structure
Platform: UNKNOWN
Classifier: Development Status :: 5 - Production/Stable
Classifier: Intended Audience :: Education
Classifier: Operating System :: Microsoft :: Windows :: Windows 10
Classifier: License :: OSI Approved :: MIT License
Classifier: Programming Language :: Python :: 3
